srisum/__init__.py
srisum/__main__.py
srisum-1.0.1.dist-info/COPYING
srisum-1.0.1.dist-info/METADATA
srisum-1.0.1.dist-info/WHEEL
srisum-1.0.1.dist-info/entry_points.txt
srisum-1.0.1.dist-info/top_level.txt
srisum-1.0.1.dist-info/RECORD
